fooster_db-0.10.0-py3.9-nspkg.pth
fooster/db/__init__.py
fooster_db-0.10.0.dist-info/LICENSE
fooster_db-0.10.0.dist-info/METADATA
fooster_db-0.10.0.dist-info/WHEEL
fooster_db-0.10.0.dist-info/namespace_packages.txt
fooster_db-0.10.0.dist-info/top_level.txt
fooster_db-0.10.0.dist-info/RECORD
